modelsim/wave_test.v
module wave_test;
    reg clk = 0;
    reg rst = 0;
    reg [3:0] counter = 0;

    always #5 clk = ~clk;

    always @(posedge clk) begin
        if (rst) counter <= 0;
        else     counter <= counter + 1;
    end

    initial begin
        $dumpfile("wave_test.vcd");    // VCD 파일 이름
        $dumpvars(0, wave_test);  // 모듈 전체 신호 덤프
        #100;
        $finish;
    end
endmodule

modelsim/wave_test.vcd
$date
	Sat May 03 00:51:30 2025
$end
$version
	Icarus Verilog
$end
$timescale
	1s
$end
$scope module wave_test $end
$var reg 1 ! clk $end
$var reg 4 " counter [3:0] $end
$var reg 1 # rst $end
$upscope $end
$enddefinitions $end
$comment Show the parameter values. $end
$dumpall
$end
#0
$dumpvars
0#
b0 "
0!
$end
#5
b1 "
1!
#10
0!
#15
b10 "
1!
#20
0!
#25
b11 "
1!
#30
0!
#35
b100 "
1!
#40
0!
#45
b101 "
1!
#50
0!
#55
b110 "
1!
#60
0!
#65
b111 "
1!
#70
0!
#75
b1000 "
1!
#80
0!
#85
b1001 "
1!
#90
0!
#95
b1010 "
1!
